shub_image/__init__.py
shub_image/build.py
shub_image/check.py
shub_image/deploy.py
shub_image/init.py
shub_image/list.py
shub_image/push.py
shub_image/test.py
shub_image/tool.py
shub_image/upload.py
shub_image/utils.py
shub_image-0.2.5.dist-info/DESCRIPTION.rst
shub_image-0.2.5.dist-info/METADATA
shub_image-0.2.5.dist-info/RECORD
shub_image-0.2.5.dist-info/WHEEL
shub_image-0.2.5.dist-info/entry_points.txt
shub_image-0.2.5.dist-info/metadata.json
shub_image-0.2.5.dist-info/top_level.txt
