Metadata-Version: 2.0
Name: shub-image
Version: 0.2.5
Summary: Scrapinghub release tool
Home-page: UNKNOWN
Author: Scrapinghub
Author-email: info@scrapinghub.com
License: BSD
Platform: UNKNOWN
Classifier: Development Status :: 5 - Production/Stable
Classifier: Intended Audience :: Developers
Classifier: Natural Language :: English
Classifier: License :: OSI Approved :: BSD License
Classifier: Programming Language :: Python
Classifier: Programming Language :: Python :: 2.7
Classifier: Operating System :: OS Independent
Classifier: Environment :: Console
Classifier: Topic :: Internet :: WWW/HTTP
Requires-Dist: click
Requires-Dist: docker-py
Requires-Dist: requests
Requires-Dist: shub (>=0.2.5)
Requires-Dist: six
